{
  "asset": "thBILL",
  "vault_address": "0x5fa487bca6158c64046b2813623e20755091da0b",
  "treasury_address": "0xAECCa546baFB16735b273702632C8Cbb83509d8F",
  "timestamp": "2026-02-18T22:20:02.116593",
  "tvl_usd": {
    "total": 129298187.10231,
    "by_chain": {
      "Arbitrum": 36515240.43667,
      "Solana": 25925450,
      "Ethereum": 66857496.66564
    }
  },
  "backing": {
    "tultra_supply": 155107427.614248,
    "tultra_vault_balance": 155107427.614248,
    "ultra_ethereum": 64829824.266422,
    "ultra_arbitrum": 36192127.917021,
    "ultra_solana": 25000000.0,
    "ultra_total": 126021952.18344301,
    "treasury_ultra_ethereum": 64463683.854454,
    "treasury_ultra_arbitrum": 35211771.094299,
    "treasury_ultra_solana": 25000000.0,
    "treasury_ultra_total": 124675454.948753,
    "treasury_usdc": 7497.763014,
    "treasury_defi_positions": null,
    "thbill_supply": 157749372.428557,
    "implied_cash": 29085475.430804998,
    "backing_ratio_ultra_only": 0.798874507348782,
    "backing_ratio_with_usdc": 0.798922036938907,
    "note": "Treasury USDC includes spot balances + DeFi positions (Aave) via DeBank"
  },
  "theo_reported": null,
  "redemption_flow": {
    "net_flow_24h": 0.0,
    "net_flow_percentage": 0.0,
    "supply_24h_ago": 157749372.428557,
    "current_supply": 157749372.428557,
    "note": null
  },
  "secondary_liquidity": {
    "total_volume_24h": 1395983.85,
    "total_tvl_usd": 3578402.8463181322,
    "pools": [
      {
        "market": "Uniswap V3 (Arbitrum One)",
        "chain": "arbitrum",
        "pair": "0XFDD22CE6D1F66BC0EC89B20BF16CCB6670F55A5A/0XAF88D065E77C8CC2239327C5EDB3A432268E5831",
        "volume_24h": 1123697,
        "tvl_usd": 2138235,
        "depth_2pct_buy": 1279384.082031,
        "depth_2pct_sell": 561617.822265,
        "spread": 0.602854,
        "last_price": 1.0139798619,
        "trust_score": "green",
        "aggregators": null
      },
      {
        "market": "Project X",
        "chain": "hyperevm",
        "pair": "0X111111A1A0667D36BD57C0A9F569B98057111111/0XFDD22CE6D1F66BC0EC89B20BF16CCB6670F55A5A",
        "volume_24h": 3211.0,
        "tvl_usd": 40612.302479,
        "depth_2pct_buy": null,
        "depth_2pct_sell": null,
        "spread": 0.607732,
        "last_price": 1.014650862402602,
        "trust_score": "yellow",
        "aggregators": null
      },
      {
        "market": "Project X (+3 aggregators)",
        "chain": "hyperevm",
        "pair": "0XB8CE59FC3717ADA4C02EADF9682A9E934F625EBB/0XFDD22CE6D1F66BC0EC89B20BF16CCB6670F55A5A",
        "volume_24h": 258801.14,
        "tvl_usd": 1358610.401319,
        "depth_2pct_buy": 283605.465697,
        "depth_2pct_sell": 1064542.480468,
        "spread": 0.602897,
        "last_price": 1.0146586068956738,
        "trust_score": null,
        "aggregators": [
          "Upheaval Finance",
          "UltraSolid V3",
          "HyperSwap V3",
          "Project X"
        ]
      },
      {
        "market": "Project X",
        "chain": "hyperevm",
        "pair": "0XB88339CB7199B77E23DB6E890353E22632BA630F/0XFDD22CE6D1F66BC0EC89B20BF16CCB6670F55A5A",
        "volume_24h": 3494.98,
        "tvl_usd": 6129.738152,
        "depth_2pct_buy": 1625.863646,
        "depth_2pct_sell": 4677.590941,
        "spread": 0.644404,
        "last_price": 1.014434910794508,
        "trust_score": "green",
        "aggregators": null
      },
      {
        "market": "Project X",
        "chain": "hyperevm",
        "pair": "0XFD739D4E423301CE9385C1FB8850539D657C296D/0XFDD22CE6D1F66BC0EC89B20BF16CCB6670F55A5A",
        "volume_24h": 1193.14,
        "tvl_usd": 853.7358297487749,
        "depth_2pct_buy": null,
        "depth_2pct_sell": null,
        "spread": 0.649465,
        "last_price": 0.03516826621217499,
        "trust_score": "green",
        "aggregators": null
      },
      {
        "market": "Project X",
        "chain": "hyperevm",
        "pair": "0XFDD22CE6D1F66BC0EC89B20BF16CCB6670F55A5A/0X5555555555555555555555555555555555555555",
        "volume_24h": 1149.79,
        "tvl_usd": 971.6673943837656,
        "depth_2pct_buy": null,
        "depth_2pct_sell": null,
        "spread": 0.851056,
        "last_price": 0.03554391902,
        "trust_score": "green",
        "aggregators": null
      },
      {
        "market": "Uniswap V3 (Ethereum)",
        "chain": "ethereum",
        "pair": "0X5FA487BCA6158C64046B2813623E20755091DA0B/0XA0B86991C6218B36C1D19D4A2E9EB0CE3606EB48",
        "volume_24h": 4436.8,
        "tvl_usd": 32990.001144,
        "depth_2pct_buy": 2846.554564,
        "depth_2pct_sell": 8950.009154,
        "spread": 0.617003,
        "last_price": 1.0131587929,
        "trust_score": "yellow",
        "aggregators": null
      }
    ]
  },
  "peg": {
    "nav_per_share": 1.018285,
    "vwap": 1.014106,
    "premium_discount_pct": -0.4104,
    "per_chain_prices": {
      "Arbitrum": {
        "vwap": 1.01398,
        "volume_24h": 1123697.0
      },
      "HyperEVM": {
        "vwap": 1.014656,
        "volume_24h": 265507.12
      },
      "Ethereum": {
        "vwap": 1.013159,
        "volume_24h": 4436.8
      }
    }
  },
  "defi_markets": [
    {
      "protocol": "pendle",
      "chain": "Arbitrum",
      "pool": "THBILL",
      "tvl_usd": 12547718,
      "apy": 5.62009,
      "apy_base": 5.28717,
      "apy_reward": 0.33291,
      "pool_meta": "For LP | Maturity 19FEB2026"
    },
    {
      "protocol": "pendle",
      "chain": "Arbitrum",
      "pool": "THBILL",
      "tvl_usd": 12547718,
      "apy": 12.1692,
      "apy_base": 12.1692,
      "apy_reward": null,
      "pool_meta": "For buying PT-thBILL-19FEB2026"
    },
    {
      "protocol": "morpho-v1",
      "chain": "Arbitrum",
      "pool": "THBILL",
      "tvl_usd": 10356343,
      "apy": 0,
      "apy_base": null,
      "apy_reward": null,
      "pool_meta": null
    },
    {
      "protocol": "morpho-v1",
      "chain": "Arbitrum",
      "pool": "PT-THBILL-19FEB2026",
      "tvl_usd": 3863737,
      "apy": 0,
      "apy_base": null,
      "apy_reward": null,
      "pool_meta": null
    },
    {
      "protocol": "uniswap-v3",
      "chain": "Arbitrum",
      "pool": "USDC-THBILL",
      "tvl_usd": 2138235,
      "apy": 0,
      "apy_base": 0,
      "apy_reward": null,
      "pool_meta": "0.01%"
    },
    {
      "protocol": "pendle",
      "chain": "Arbitrum",
      "pool": "THBILL",
      "tvl_usd": 1981851,
      "apy": 6.88014,
      "apy_base": 2.64579,
      "apy_reward": 4.23435,
      "pool_meta": "For LP | Maturity 18JUN2026"
    },
    {
      "protocol": "pendle",
      "chain": "Arbitrum",
      "pool": "THBILL",
      "tvl_usd": 1981851,
      "apy": 4.36596,
      "apy_base": 4.36596,
      "apy_reward": null,
      "pool_meta": "For buying PT-thBILL-18JUN2026"
    },
    {
      "protocol": "euler-v2",
      "chain": "Arbitrum",
      "pool": "THBILL",
      "tvl_usd": 1620742,
      "apy": 3.74699,
      "apy_base": 3.74699,
      "apy_reward": null,
      "pool_meta": "EVK Vault ethBILL-2"
    },
    {
      "protocol": "project-x",
      "chain": "Hyperliquid L1",
      "pool": "USD\u20ae0-THBILL",
      "tvl_usd": 1389180,
      "apy": 0.56298,
      "apy_base": 0.56298,
      "apy_reward": null,
      "pool_meta": "0.01%"
    },
    {
      "protocol": "morpho-v1",
      "chain": "Hyperliquid L1",
      "pool": "THBILL",
      "tvl_usd": 1237903,
      "apy": 0,
      "apy_base": null,
      "apy_reward": null,
      "pool_meta": null
    },
    {
      "protocol": "morpho-v1",
      "chain": "Ethereum",
      "pool": "THBILL",
      "tvl_usd": 170138,
      "apy": 0,
      "apy_base": null,
      "apy_reward": null,
      "pool_meta": null
    },
    {
      "protocol": "project-x",
      "chain": "Hyperliquid L1",
      "pool": "USDH-THBILL",
      "tvl_usd": 40758,
      "apy": 0.24539,
      "apy_base": 0.24539,
      "apy_reward": null,
      "pool_meta": "0.01%"
    },
    {
      "protocol": "project-x",
      "chain": "Hyperliquid L1",
      "pool": "KHYPE-THBILL",
      "tvl_usd": 27256,
      "apy": 3.75812,
      "apy_base": 3.75812,
      "apy_reward": null,
      "pool_meta": "0.3%"
    },
    {
      "protocol": "project-x",
      "chain": "Hyperliquid L1",
      "pool": "WHYPE-THBILL",
      "tvl_usd": 25783,
      "apy": 4.01277,
      "apy_base": 4.01277,
      "apy_reward": null,
      "pool_meta": "0.3%"
    }
  ]
}